[
  {
    "posterImage": "https://i.ibb.co.com/RTysSM9s/images.jpg",
    "posterName": "Avatar 3: The Seed Bearer",
    "hits": 982345,
    "releaseDay": 14
  },
  {
    "posterImage": "https://i.ibb.co.com/PGL3X0Qb/MV5-BNWM2-MTU4-NGMt-Ym-Rl-NC00-ZTU4-LThm-MGYt-Mm-Fh-YTIx-NDY2-Mj-Y1-Xk-Ey-Xk-Fqc-Gde-QWFs-ZWxv-Zw-V1.jpg",
    "posterName": "Spider-Man 4: Beyond the Web",
    "hits": 876543,
    "releaseDay": 7
  },
  {
    "posterImage": "https://i.ibb.co.com/PGmw2p9T/mcu-avengers-secret-wars-2027-fan-casting-poster-396666-large.jpg",
    "posterName": "Avengers: Secret Wars",
    "hits": 765432,
    "releaseDay": 21
  },
  {
    "posterImage": "https://i.ibb.co.com/Q7JcR1dc/John-Wick-Chapter-4.webp",
    "posterName": "John Wick 5: Redemption",
    "hits": 654321,
    "releaseDay": 10
  },
  {
    "posterImage": "https://i.ibb.co.com/8g0t0Zw8/6-B59664-A-8-DFF-474-C-99-F4-6-CE3-FF863848.jpg",
    "posterName": "Black Panther: Wakanda Forever Part 2",
    "hits": 543210,
    "releaseDay": 28
  },
 
  {
    "posterImage": "https://i.ibb.co.com/sJHF6KKt/bpzhlyb2l9za1.jpg",
    "posterName": "Guardians of the Galaxy Vol. 4",
    "hits": 321098,
    "releaseDay": 12
  },
  {
    "posterImage": "https://i.ibb.co.com/RkSkBt5t/fast11.webp",
    "posterName": "Fast & Furious 11: Final Ride",
    "hits": 210987,
    "releaseDay": 19
  }
  
]
